optrix/__init__.py
optrix/_objects.py
Optrix-0.0.1.dist-info/LICENSE
Optrix-0.0.1.dist-info/METADATA
Optrix-0.0.1.dist-info/WHEEL
Optrix-0.0.1.dist-info/top_level.txt
Optrix-0.0.1.dist-info/RECORD
