Metadata-Version: 2.1
Name: Optrix
Version: 0.0.1
Summary: Optics Package
Author-email: João Biu <joaopedrofbiu@tecnico.ulisboa.pt>
Classifier: Programming Language :: Python :: 3
Classifier: License :: OSI Approved :: MIT License
Classifier: Operating System :: OS Independent
Requires-Python: >=3.12
License-File: LICENSE
